{"updated":1783031881,"source":"abuse.ch / ThreatFox","count":40,"iocs":[{"ioc":"165.227.194[.]213:5555","type":"ip:port","malware":"Aisuru","confidence":100,"first_seen":"2026-07-02 22:33:08 UTC"},{"ioc":"185.192.124[.]218:4291","type":"ip:port","malware":"NjRAT","confidence":99,"first_seen":"2026-07-02 22:16:34 UTC"},{"ioc":"158.160.75[.]185:43082","type":"ip:port","malware":"NjRAT","confidence":99,"first_seen":"2026-07-02 22:16:12 UTC"},{"ioc":"pmaumei.1xgame[.]bet","type":"domain","malware":"ClearFake","confidence":100,"first_seen":"2026-07-02 22:14:44 UTC"},{"ioc":"1xgame[.]bet","type":"domain","malware":"ClearFake","confidence":100,"first_seen":"2026-07-02 22:13:29 UTC"},{"ioc":"tearmbdo.bet1forward[.]com","type":"domain","malware":"ClearFake","confidence":100,"first_seen":"2026-07-02 22:13:23 UTC"},{"ioc":"qlrjloxh.jozve[.]one","type":"domain","malware":"ClearFake","confidence":100,"first_seen":"2026-07-02 22:11:55 UTC"},{"ioc":"jozve[.]one","type":"domain","malware":"ClearFake","confidence":100,"first_seen":"2026-07-02 22:10:14 UTC"},{"ioc":"firmwareupdatechecksdoidv2627[.]buzz","type":"domain","malware":"Mirai","confidence":100,"first_seen":"2026-07-02 22:10:05 UTC"},{"ioc":"gold-land-8.vortex-sys.in[.]net","type":"domain","malware":"ClearFake","confidence":90,"first_seen":"2026-07-02 22:05:12 UTC"},{"ioc":"154.220.95[.]126:8888","type":"ip:port","malware":"Unknown malware","confidence":100,"first_seen":"2026-07-02 22:05:05 UTC"},{"ioc":"betwinner[.]bet","type":"domain","malware":"ClearFake","confidence":100,"first_seen":"2026-07-02 22:01:34 UTC"},{"ioc":"clickhitriver[.]com","type":"domain","malware":"Unknown malware","confidence":100,"first_seen":"2026-07-02 22:00:15 UTC"},{"ioc":"188.190.9[.]177:443","type":"ip:port","malware":"FAKEUPDATES","confidence":100,"first_seen":"2026-07-02 21:53:34 UTC"},{"ioc":"165.227.194[.]213:9035","type":"ip:port","malware":"Aisuru","confidence":100,"first_seen":"2026-07-02 21:47:03 UTC"},{"ioc":"cashorix[.]xyz","type":"domain","malware":"Unknown Stealer","confidence":100,"first_seen":"2026-07-02 21:39:02 UTC"},{"ioc":"hxxps://her[.]psgiran[.]news/","type":"url","malware":"Vidar","confidence":100,"first_seen":"2026-07-02 21:30:19 UTC"},{"ioc":"hxxps://her[.]jokimecat88[.]top/","type":"url","malware":"Vidar","confidence":100,"first_seen":"2026-07-02 21:30:18 UTC"},{"ioc":"her.psgiran[.]news","type":"domain","malware":"Vidar","confidence":100,"first_seen":"2026-07-02 21:30:18 UTC"},{"ioc":"her.jokimecat88[.]top","type":"domain","malware":"Vidar","confidence":100,"first_seen":"2026-07-02 21:30:17 UTC"},{"ioc":"flhrpdn.yekbetkade[.]com","type":"domain","malware":"ClearFake","confidence":100,"first_seen":"2026-07-02 21:15:34 UTC"},{"ioc":"yekbetkade[.]com","type":"domain","malware":"ClearFake","confidence":100,"first_seen":"2026-07-02 21:13:57 UTC"},{"ioc":"154.220.93[.]235:8888","type":"ip:port","malware":"Unknown malware","confidence":100,"first_seen":"2026-07-02 21:05:09 UTC"},{"ioc":"154.220.123[.]189:8888","type":"ip:port","malware":"Unknown malware","confidence":100,"first_seen":"2026-07-02 21:05:08 UTC"},{"ioc":"154.220.122[.]107:8888","type":"ip:port","malware":"Unknown malware","confidence":100,"first_seen":"2026-07-02 21:05:07 UTC"},{"ioc":"154.220.122[.]114:8888","type":"ip:port","malware":"Unknown malware","confidence":100,"first_seen":"2026-07-02 21:05:07 UTC"},{"ioc":"154.220.121[.]50:8888","type":"ip:port","malware":"Unknown malware","confidence":100,"first_seen":"2026-07-02 21:05:05 UTC"},{"ioc":"rfedpuuc.falsafekonkour[.]site","type":"domain","malware":"ClearFake","confidence":100,"first_seen":"2026-07-02 21:03:15 UTC"},{"ioc":"139.59.247[.]238:9035","type":"ip:port","malware":"Aisuru","confidence":100,"first_seen":"2026-07-02 21:00:45 UTC"},{"ioc":"bkscndcloud[.]beer","type":"domain","malware":"Unknown Stealer","confidence":100,"first_seen":"2026-07-02 21:00:09 UTC"},{"ioc":"143.244.175[.]246:9035","type":"ip:port","malware":"Aisuru","confidence":100,"first_seen":"2026-07-02 20:57:26 UTC"},{"ioc":"noir-5.vortex-sys.in[.]net","type":"domain","malware":"ClearFake","confidence":90,"first_seen":"2026-07-02 20:40:11 UTC"},{"ioc":"137.184.74[.]12:8443","type":"ip:port","malware":"Aisuru","confidence":100,"first_seen":"2026-07-02 20:37:04 UTC"},{"ioc":"lbftpzh.takbetkade[.]com","type":"domain","malware":"ClearFake","confidence":100,"first_seen":"2026-07-02 20:14:18 UTC"},{"ioc":"139.59.247[.]238:8080","type":"ip:port","malware":"Aisuru","confidence":100,"first_seen":"2026-07-02 20:10:16 UTC"},{"ioc":"154.220.123[.]170:8888","type":"ip:port","malware":"Unknown malware","confidence":100,"first_seen":"2026-07-02 20:05:05 UTC"},{"ioc":"154.220.123[.]165:8888","type":"ip:port","malware":"Unknown malware","confidence":100,"first_seen":"2026-07-02 20:05:04 UTC"},{"ioc":"178.128.209[.]167:8443","type":"ip:port","malware":"Aisuru","confidence":100,"first_seen":"2026-07-02 19:55:23 UTC"},{"ioc":"mlvgwjn.1xforward[.]pro","type":"domain","malware":"ClearFake","confidence":100,"first_seen":"2026-07-02 19:54:24 UTC"},{"ioc":"137.184.74[.]12:5555","type":"ip:port","malware":"Aisuru","confidence":100,"first_seen":"2026-07-02 19:52:01 UTC"}]}