{"updated":1782882413,"source":"abuse.ch / ThreatFox","count":40,"iocs":[{"ioc":"129.212.233[.]8:9035","type":"ip:port","malware":"Aisuru","confidence":100,"first_seen":"2026-07-01 05:02:36 UTC"},{"ioc":"130.94.66[.]70:2087","type":"ip:port","malware":"VShell","confidence":100,"first_seen":"2026-07-01 04:05:07 UTC"},{"ioc":"207.57.128[.]240:18084","type":"ip:port","malware":"VShell","confidence":100,"first_seen":"2026-07-01 04:05:07 UTC"},{"ioc":"117.72.158[.]44:8080","type":"ip:port","malware":"VShell","confidence":100,"first_seen":"2026-07-01 04:05:06 UTC"},{"ioc":"101.43.128[.]56:80","type":"ip:port","malware":"VShell","confidence":100,"first_seen":"2026-07-01 04:05:05 UTC"},{"ioc":"njb2hl8n.betobord[.]live","type":"domain","malware":"ClearFake","confidence":100,"first_seen":"2026-07-01 02:33:39 UTC"},{"ioc":"betobord[.]live","type":"domain","malware":"ClearFake","confidence":100,"first_seen":"2026-07-01 02:30:58 UTC"},{"ioc":"cxsbf6om.betmajickade[.]com","type":"domain","malware":"ClearFake","confidence":100,"first_seen":"2026-07-01 02:26:49 UTC"},{"ioc":"betmajickade[.]com","type":"domain","malware":"ClearFake","confidence":100,"first_seen":"2026-07-01 02:26:41 UTC"},{"ioc":"q08rvd2u.btyek[.]bond","type":"domain","malware":"ClearFake","confidence":100,"first_seen":"2026-07-01 02:11:47 UTC"},{"ioc":"btyek[.]bond","type":"domain","malware":"ClearFake","confidence":100,"first_seen":"2026-07-01 02:08:46 UTC"},{"ioc":"podcas-watch.to6varil.in[.]net","type":"domain","malware":"ClearFake","confidence":90,"first_seen":"2026-07-01 01:59:05 UTC"},{"ioc":"publ1-wave.kymle5rax.in[.]net","type":"domain","malware":"ClearFake","confidence":90,"first_seen":"2026-07-01 01:59:05 UTC"},{"ioc":"lette-logic.to6varil.in[.]net","type":"domain","malware":"ClearFake","confidence":90,"first_seen":"2026-07-01 01:59:04 UTC"},{"ioc":"it5ut2.to6varil.in[.]net","type":"domain","malware":"ClearFake","confidence":90,"first_seen":"2026-07-01 01:59:04 UTC"},{"ioc":"sabad724[.]xyz","type":"domain","malware":"ClearFake","confidence":90,"first_seen":"2026-07-01 01:54:04 UTC"},{"ioc":"btyek[.]xyz","type":"domain","malware":"ClearFake","confidence":90,"first_seen":"2026-07-01 01:54:04 UTC"},{"ioc":"onebet1x[.]bet","type":"domain","malware":"ClearFake","confidence":90,"first_seen":"2026-07-01 01:44:04 UTC"},{"ioc":"rlhk5nxo.ra7ximor.in[.]net","type":"domain","malware":"ClearFake","confidence":90,"first_seen":"2026-07-01 01:44:03 UTC"},{"ioc":"darklistener.ra7ximor.in[.]net","type":"domain","malware":"ClearFake","confidence":90,"first_seen":"2026-07-01 01:44:03 UTC"},{"ioc":"ser-spireal.sylov2en.in[.]net","type":"domain","malware":"ClearFake","confidence":90,"first_seen":"2026-07-01 01:44:03 UTC"},{"ioc":"ipynzqk.sylov2en.in[.]net","type":"domain","malware":"ClearFake","confidence":90,"first_seen":"2026-07-01 01:44:03 UTC"},{"ioc":"1xfa[.]xyz","type":"domain","malware":"ClearFake","confidence":90,"first_seen":"2026-07-01 01:44:03 UTC"},{"ioc":"repairwoo.sylov2en.in[.]net","type":"domain","malware":"ClearFake","confidence":90,"first_seen":"2026-07-01 01:44:03 UTC"},{"ioc":"fernvalidator.ra7ximor.in[.]net","type":"domain","malware":"ClearFake","confidence":90,"first_seen":"2026-07-01 01:39:02 UTC"},{"ioc":"gre-enleaf2.4zorexil.in[.]net","type":"domain","malware":"ClearFake","confidence":90,"first_seen":"2026-07-01 01:39:01 UTC"},{"ioc":"plinko[.]mobi","type":"domain","malware":"ClearFake","confidence":90,"first_seen":"2026-07-01 01:39:01 UTC"},{"ioc":"dr1v-cache.4zorexil.in[.]net","type":"domain","malware":"ClearFake","confidence":90,"first_seen":"2026-07-01 01:39:01 UTC"},{"ioc":"nysaaol7.4zorexil.in[.]net","type":"domain","malware":"ClearFake","confidence":90,"first_seen":"2026-07-01 01:39:01 UTC"},{"ioc":"clientlab.4zorexil.in[.]net","type":"domain","malware":"ClearFake","confidence":90,"first_seen":"2026-07-01 01:39:01 UTC"},{"ioc":"daf[.]bet","type":"domain","malware":"ClearFake","confidence":90,"first_seen":"2026-07-01 01:39:00 UTC"},{"ioc":"sweetpear2.sylov2en.in[.]net","type":"domain","malware":"ClearFake","confidence":90,"first_seen":"2026-07-01 01:34:00 UTC"},{"ioc":"tasty-apple1.sylov2en.in[.]net","type":"domain","malware":"ClearFake","confidence":90,"first_seen":"2026-07-01 01:34:00 UTC"},{"ioc":"newpage6.ra7ximor.in[.]net","type":"domain","malware":"ClearFake","confidence":90,"first_seen":"2026-07-01 01:34:00 UTC"},{"ioc":"blue-sky1.4zorexil.in[.]net","type":"domain","malware":"ClearFake","confidence":90,"first_seen":"2026-07-01 01:34:00 UTC"},{"ioc":"freshm-ilk3.sylov2en.in[.]net","type":"domain","malware":"ClearFake","confidence":90,"first_seen":"2026-07-01 01:29:00 UTC"},{"ioc":"coolstone6.sylov2en.in[.]net","type":"domain","malware":"ClearFake","confidence":90,"first_seen":"2026-07-01 01:28:59 UTC"},{"ioc":"warmbr-ead5.sylov2en.in[.]net","type":"domain","malware":"ClearFake","confidence":90,"first_seen":"2026-07-01 01:28:59 UTC"},{"ioc":"hottea4.sylov2en.in[.]net","type":"domain","malware":"ClearFake","confidence":90,"first_seen":"2026-07-01 01:28:59 UTC"},{"ioc":"darknight2.to6varil.in[.]net","type":"domain","malware":"ClearFake","confidence":90,"first_seen":"2026-07-01 01:23:59 UTC"}]}